thumbup/Job.py
thumbup/Processor.py
thumbup/__init__.py
thumbup/cmd_line.py
thumbup-1.5.1.dist-info/LICENSE
thumbup-1.5.1.dist-info/METADATA
thumbup-1.5.1.dist-info/WHEEL
thumbup-1.5.1.dist-info/entry_points.txt
thumbup-1.5.1.dist-info/top_level.txt
thumbup-1.5.1.dist-info/RECORD
