Metadata-Version: 2.1
Name: thumbup
Version: 1.5.1
Summary: A convenient video thumbnails generator.
Home-page: https://github.com/bl4ck5un/thumbup.py
Author: Fan Zhang
Author-email: bl4ck5unxx@gmail.com
License: MIT
Keywords: video thumbnail snapshot
Platform: UNKNOWN
Classifier: Development Status :: 3 - Alpha
Classifier: Intended Audience :: End Users/Desktop
Classifier: Topic :: Multimedia :: Video
Classifier: Topic :: Utilities
Classifier: License :: OSI Approved :: MIT License
Classifier: Programming Language :: Python :: 3
Classifier: Programming Language :: Python :: 3.7
Requires-Dist: Pillow
Requires-Dist: av
Requires-Dist: numpy
